exogibbs/__init__.py
exogibbs/exogibbs_version.py
exogibbs/api/__init__.py
exogibbs/api/chemistry.py
exogibbs/api/equilibrium.py
exogibbs/data/fastchem/README.md
exogibbs/data/fastchem/logK/README.TXT
exogibbs/data/fastchem/logK/logK.dat
exogibbs/data/fastchem/logK/logK_condensates.dat
exogibbs/data/fastchem/logK/logK_extended.dat
exogibbs/data/fastchem/logK/logK_wo_ions.dat
exogibbs/data/test/janaf_raw_sample.txt
exogibbs/data/test/matrix_v3.dat
exogibbs/data/test/testdata.dat
exogibbs/data/ykb4/gibbs_matrices.npz
exogibbs/data/ykb4/molecule_names.csv
exogibbs/equilibrium/__init__.py
exogibbs/equilibrium/gibbs.py
exogibbs/io/__init__.py
exogibbs/io/load_data.py
exogibbs/optimize/__init__.py
exogibbs/optimize/core.py
exogibbs/optimize/minimize.py
exogibbs/optimize/vjpgibbs.py
exogibbs/presets/__init__.py
exogibbs/presets/fastchem.py
exogibbs/presets/ykb4.py
exogibbs/test/__init__.py
exogibbs/test/analytic_hcosystem.py
exogibbs/test/analytic_hsystem.py
exogibbs/test/generate_gibbs.py
exogibbs/test/reference_data.py
exogibbs/thermo/__init__.py
exogibbs/thermo/stoichiometry.py
exogibbs/utils/__init__.py
exogibbs/utils/constants.py
exogibbs-0.3.0.dist-info/licenses/LICENSE
exogibbs-0.3.0.dist-info/METADATA
exogibbs-0.3.0.dist-info/WHEEL
exogibbs-0.3.0.dist-info/top_level.txt
exogibbs-0.3.0.dist-info/RECORD
